{
  "version": "1.0.0",
  "goal": 500,
  "currentScore": 420,
  "sessions": [
    {
      "date": "2026-02-01",
      "session": 1,
      "bugsFound": {
        "critical": 0,
        "high": 0,
        "medium": 0,
        "low": 0
      },
      "patternsApplied": [],
      "patternsCaughtBugs": [],
      "newPatternsAdded": 20,
      "scoreChange": 500,
      "runningScore": 500,
      "notes": "Initial setup - created 20 patterns based on recent fixes"
    },
    {
      "date": "2026-02-01",
      "session": 2,
      "bugsFound": {
        "critical": 0,
        "high": 2,
        "medium": 0,
        "low": 0
      },
      "patternsApplied": ["P003", "P009", "P010", "P012", "P020"],
      "patternsCaughtBugs": ["P010", "P010"],
      "newPatternsAdded": 0,
      "scoreChange": -80,
      "runningScore": 420,
      "notes": "QA run - P010 caught 2 missing large transaction confirmations"
    }
  ],
  "scoring": {
    "penalties": {
      "CRITICAL": -100,
      "HIGH": -50,
      "MEDIUM": -20,
      "LOW": -5
    },
    "rewards": {
      "noNewBugs": 200,
      "fewerBugsThanLastSession": 100,
      "patternCaughtBug": 10,
      "newPatternAdded": 25
    }
  },
  "stats": {
    "totalSessions": 2,
    "totalBugsFound": 2,
    "totalBugsFixed": 2,
    "totalPatternsCreated": 20,
    "mostEffectivePatterns": ["P010", "P003", "P018", "P019", "P012"]
  }
}
